neon_minerva/__init__.py
neon_minerva/cli.py
neon_minerva/exceptions.py
neon_minerva/skill.py
neon_minerva/version.py
neon_minerva/chatbots/__init__.py
neon_minerva/chatbots/test_constants.py
neon_minerva/chatbots/util.py
neon_minerva/integration/__init__.py
neon_minerva/integration/rabbit_mq.py
neon_minerva/integration/user_utterance.py
neon_minerva/intent_services/__init__.py
neon_minerva/intent_services/adapt.py
neon_minerva/intent_services/common_query.py
neon_minerva/intent_services/padacioso.py
neon_minerva/intent_services/padatious.py
neon_minerva/tests/__init__.py
neon_minerva/tests/chatbot_v1_test_base.py
neon_minerva/tests/skill_unit_test_base.py
neon_minerva/tests/test_skill_intents.py
neon_minerva/tests/test_skill_resources.py
neon_minerva-0.3.0.dist-info/LICENSE.md
neon_minerva-0.3.0.dist-info/METADATA
neon_minerva-0.3.0.dist-info/WHEEL
neon_minerva-0.3.0.dist-info/entry_points.txt
neon_minerva-0.3.0.dist-info/top_level.txt
neon_minerva-0.3.0.dist-info/RECORD
