Metadata-Version: 2.1
Name: neon-minerva
Version: 0.3.0
Summary: Modular INtelligent Evaluation for a Reliable Voice Assistant
Home-page: https://github.com/neongeckocom/neon-minerva
Author: Neongecko
Author-email: developers@neon.ai
License: BSD-3-Clause
Classifier: Programming Language :: Python :: 3
Classifier: Operating System :: OS Independent
Requires-Python: >=3.6
License-File: LICENSE.md
Requires-Dist: click~=8.0
Requires-Dist: click-default-group~=1.2
Requires-Dist: ovos-utils>=0.0.35,~=0.0
Requires-Dist: ovos-workshop>=0.0.15,~=0.0
Requires-Dist: ovos-bus-client~=0.0
Requires-Dist: padacioso~=0.1
Requires-Dist: pyyaml<7.0,>=5.4
Provides-Extra: chatbots
Requires-Dist: klat-connector; extra == "chatbots"
Requires-Dist: neon-chatbot-core; extra == "chatbots"
Provides-Extra: padatious
Requires-Dist: padatious~=0.4.8; extra == "padatious"
Requires-Dist: fann2==1.0.7; extra == "padatious"
Provides-Extra: rmq
Requires-Dist: pytest-rabbitmq~=3.0; extra == "rmq"
